setup.cfg
setup.py
mongate/__init__.py
mongate/batch.py
mongate/collection.py
mongate/connection.py
mongate/database.py
mongate.egg-info/PKG-INFO
mongate.egg-info/SOURCES.txt
mongate.egg-info/dependency_links.txt
mongate.egg-info/requires.txt
mongate.egg-info/top_level.txt
tests/__init__.py
tests/test_batch.py
tests/test_collection.py
tests/test_connection.py
tests/test_database.py