Metadata-Version: 1.0
Name: mongate
Version: 2.1.6
Summary: A client library for Sleepy Mongoose that provides the same interface as Pymongo. With support for batch operations.
Home-page: https://github.com/bcoe/mongate
Author: Benjamin Coe
Author-email: bencoe@gmail.com
License: UNKNOWN
Platform: UNKNOWN
